Metadata-Version: 2.1
Name: chat_with_mlx
Version: 0.2.2
Summary: A Retrieval-augmented Generation (RAG) chat interface with support for multiple open-source models, designed to run natively on MacOS and Apple Silicon with MLX.
Author-email: Quan Nguyen <quanjenkey@gmail.com>
License: MIT License
Keywords: mlx,chat,chatbot,chat_with_mlx,chat_with_mlx
Classifier: Development Status :: 4 - Beta
Classifier: License :: OSI Approved :: MIT License
Classifier: Operating System :: MacOS
Classifier: Programming Language :: Python :: 3
Classifier: Programming Language :: Python :: 3.8
Classifier: Programming Language :: Python :: 3.9
Classifier: Programming Language :: Python :: 3.10
Classifier: Programming Language :: Python :: 3.11
Classifier: Topic :: Scientific/Engineering :: Artificial Intelligence
Requires-Python: >=3.8
License-File: LICENSE
Requires-Dist: mlx-lm ==0.14.3
Requires-Dist: gradio ==4.29.0
Requires-Dist: tiktoken ==0.7.0
Requires-Dist: langchain ==0.1.16
Requires-Dist: langchain-community >=0.0.25
Requires-Dist: langchain-core ==0.1.45
Requires-Dist: sentence-transformers ==3.0.1
Requires-Dist: einops ==0.8.0
Requires-Dist: chromadb ==0.5.0
Requires-Dist: pypdf ==4.2.0
Requires-Dist: youtube-transcript-api ==0.6.2
Requires-Dist: sentencepiece ==0.2.0
Requires-Dist: docx2txt ==0.8
Provides-Extra: dev
Requires-Dist: pre-commit ; extra == 'dev'
Requires-Dist: ruff ; extra == 'dev'
Requires-Dist: build ; extra == 'dev'
Requires-Dist: twine ; extra == 'dev'
Requires-Dist: wheel ; extra == 'dev'
Requires-Dist: setuptools ; extra == 'dev'
Requires-Dist: tox ; extra == 'dev'
Requires-Dist: bandit ; extra == 'dev'
